pytest_threadleak.py
pytest_threadleak-0.5.0.dist-info/METADATA
pytest_threadleak-0.5.0.dist-info/WHEEL
pytest_threadleak-0.5.0.dist-info/entry_points.txt
pytest_threadleak-0.5.0.dist-info/top_level.txt
pytest_threadleak-0.5.0.dist-info/RECORD
